.DS_Store
imagecolor/__init__.py
imagecolor/average.py
imagecolor/kmeans.py
imagecolor/loadsave.py
imagecolor-1.2.1.dist-info/DESCRIPTION.rst
imagecolor-1.2.1.dist-info/METADATA
imagecolor-1.2.1.dist-info/RECORD
imagecolor-1.2.1.dist-info/WHEEL
imagecolor-1.2.1.dist-info/metadata.json
imagecolor-1.2.1.dist-info/top_level.txt
