Metadata-Version: 2.0
Name: imagecolor
Version: 1.2.1
Summary: Image color extraction
Home-page: https://github.com/Tathorack/imagecolor
Author: Rhys Hansen
Author-email: rhyshonline@gmail.com
License: MIT
Keywords: image average color
Platform: UNKNOWN
Classifier: Development Status :: 4 - Beta
Classifier: License :: OSI Approved :: MIT License
Classifier: Programming Language :: Python :: 3
Classifier: Programming Language :: Python :: 3.5
Classifier: Intended Audience :: Other Audience
Classifier: Topic :: Artistic Software
Classifier: Topic :: Multimedia :: Graphics
Requires-Dist: Pillow
